MainServiceAPI/__init__.py
MainServiceAPI/__main__.py
MainServiceAPI/_module_info.py
MainServiceAPI/android_termux/__init__.py
MainServiceAPI/info_blank.json
MainServiceAPI/linux/__init__.py
MainServiceAPI/linux/blank.service
MainServiceAPI/objects.py
MainServiceAPI/wrapper.py
MainServiceAPI/wrapper_blank.json
mainserviceapi-0.0.4.dist-info/METADATA
mainserviceapi-0.0.4.dist-info/WHEEL
mainserviceapi-0.0.4.dist-info/entry_points.txt
mainserviceapi-0.0.4.dist-info/RECORD
